Workbook

Sheet Instrucoes
A1: í
B3: Como usar esta planilha
B4: Esta pasta de trabalho tem 6 abas. Preencha os dados nas células indicadas (em AZUL) e não altere as fórmulas (em PRETO).
B6: Legenda de cores
B7: Texto AZUL = célula para você preencher (dado de entrada)
B8: Fundo AMARELO = parâmetro-chave (taxa, saldo inicial, percentual de cenário)
B9: Texto PRETO = fórmula pronta - não editar
B10: Texto VERDE = link vindo de outra aba - não editar
B11: Fundo VERMELHO = conta vencida / em atraso (formatação condicional automática)
B13: Descrição das abas
B14: 1) Movimento_Caixa_Diario: registro diário de entradas e saídas do caixa (vendas em dinheiro, cartão, PIX, sangrias, suprimentos e despesas pagas no caixa). O saldo acumulado é calculado automaticamente.
B15: 2) Contas_a_Pagar: controle de fornecedores e despesas com vencimento futuro. O status (Em Aberto / Pago / Atrasado) é calculado automaticamente com base na data de hoje.
B16: 3) Contas_a_Receber: controle de recebíveis (cartão de crédito, convênio, cheque pré-datado). Calcula o valor líquido após a taxa da operadora e o status do recebimento.
... B24: - Ajuste a alíquota de impostos (Simples Nacional) e as taxas de cartão nos parâmetros em amarelo conforme o contrato real do supermercado.

Sheet Movimento_Caixa_Diario
A1: MOVIMENTO DE CAIXA DIARIO
A3: Saldo Inicial de Caixa (R$) | B3: 0 | D3: Data de Início
A5: Data | B5: Descrição | C5: Categoria | D5: Entrada (R$) | E5: Saída (R$) | F5: Saldo Acumulado (R$)
A6: 01/01/2026 | B6: Vendas do dia - dinheiro | C6: Venda Dinheiro | D6: 0 | E6: 0 | F6: =B3+D6-E6 -> 0
F7: =F6+D7-E7 -> 0
F8: =F7+D8-E8 -> 0
F9: =F8+D9-E9 -> 0
F10: =F9+D10-E10 -> 0
F11: =F10+D11-E11 -> 0
F12: =F11+D12-E12 -> 0
F13: =F12+D13-E13 -> 0
F14: =F13+D14-E14 -> 0
F15: =F14+D15-E15 -> 0
F16: =F15+D16-E16 -> 0
F17: =F16+D17-E17 -> 0
F18: =F17+D18-E18 -> 0
... F155: =F154+D155-E155 -> 0
A157: TOTAIS | D157: =SUM(D6:D155) -> 0 | E157: =SUM(E6:E155) -> 0 | F157: =B3+D157-E157 -> 0

Sheet Contas_a_Pagar
A1: CONTAS A PAGAR
A3: Fornecedor | B3: Descrição / Nº Documento | C3: Categoria | D3: Data Emissão | E3: Data Vencimento | F3: Valor (R$) | G3: Status | H3: Data Pagamento | I3: Dias em Atraso | J3: Observações
A4: Distribuidora Alimentos LTDA | B4: NF 12345 | C4: Mercadorias/Fornecedores | D4: 05/01/2026 | E4: 20/01/2026 | F4: 3200 | G4: =IF(E4="","",IF(H4<>"","Pago",IF(E4<TODAY(),"Atrasado","Em Aberto"))) -> Em Aberto | I4: =IF(OR(E4="",H4<>""),0,IF(E4<TODAY(),TODAY()-E4,0)) -> 0 | J4: Pagamento em 3x no boleto
G5: =IF(E5="","",IF(H5<>"","Pago",IF(E5<TODAY(),"Atrasado","Em Aberto"))) | I5: =IF(OR(E5="",H5<>""),0,IF(E5<TODAY(),TODAY()-E5,0)) -> 0
G6: =IF(E6="","",IF(H6<>"","Pago",IF(E6<TODAY(),"Atrasado","Em Aberto"))) | I6: =IF(OR(E6="",H6<>""),0,IF(E6<TODAY(),TODAY()-E6,0)) -> 0
G7: =IF(E7="","",IF(H7<>"","Pago",IF(E7<TODAY(),"Atrasado","Em Aberto"))) | I7: =IF(OR(E7="",H7<>""),0,IF(E7<TODAY(),TODAY()-E7,0)) -> 0
G8: =IF(E8="","",IF(H8<>"","Pago",IF(E8<TODAY(),"Atrasado","Em Aberto"))) | I8: =IF(OR(E8="",H8<>""),0,IF(E8<TODAY(),TODAY()-E8,0)) -> 0
G9: =IF(E9="","",IF(H9<>"","Pago",IF(E9<TODAY(),"Atrasado","Em Aberto"))) | I9: =IF(OR(E9="",H9<>""),0,IF(E9<TODAY(),TODAY()-E9,0)) -> 0
G10: =IF(E10="","",IF(H10<>"","Pago",IF(E10<TODAY(),"Atrasado","Em Aberto"))) | I10: =IF(OR(E10="",H10<>""),0,IF(E10<TODAY(),TODAY()-E10,0)) -> 0
G11: =IF(E11="","",IF(H11<>"","Pago",IF(E11<TODAY(),"Atrasado","Em Aberto"))) | I11: =IF(OR(E11="",H11<>""),0,IF(E11<TODAY(),TODAY()-E11,0)) -> 0
G12: =IF(E12="","",IF(H12<>"","Pago",IF(E12<TODAY(),"Atrasado","Em Aberto"))) | I12: =IF(OR(E12="",H12<>""),0,IF(E12<TODAY(),TODAY()-E12,0)) -> 0
G13: =IF(E13="","",IF(H13<>"","Pago",IF(E13<TODAY(),"Atrasado","Em Aberto"))) | I13: =IF(OR(E13="",H13<>""),0,IF(E13<TODAY(),TODAY()-E13,0)) -> 0
G14: =IF(E14="","",IF(H14<>"","Pago",IF(E14<TODAY(),"Atrasado","Em Aberto"))) | I14: =IF(OR(E14="",H14<>""),0,IF(E14<TODAY(),TODAY()-E14,0)) -> 0
G15: =IF(E15="","",IF(H15<>"","Pago",IF(E15<TODAY(),"Atrasado","Em Aberto"))) | I15: =IF(OR(E15="",H15<>""),0,IF(E15<TODAY(),TODAY()-E15,0)) -> 0
G16: =IF(E16="","",IF(H16<>"","Pago",IF(E16<TODAY(),"Atrasado","Em Aberto"))) | I16: =IF(OR(E16="",H16<>""),0,IF(E16<TODAY(),TODAY()-E16,0)) -> 0
... G83: =IF(E83="","",IF(H83<>"","Pago",IF(E83<TODAY(),"Atrasado","Em Aberto"))) | I83: =IF(OR(E83="",H83<>""),0,IF(E83<TODAY(),TODAY()-E83,0)) -> 0
A85: Total em Aberto | F85: =SUMIFS(F4:F83,G4:G83,"Em Aberto") -> 3200
A86: Total Atrasado | F86: =SUMIFS(F4:F83,G4:G83,"Atrasado") -> 0
A87: Total Pago | F87: =SUMIFS(F4:F83,G4:G83,"Pago") -> 0

Sheet Contas_a_Receber
A1: CONTAS A RECEBER
A3: Cliente / Bandeira | B3: Descrição | C3: Categoria | D3: Data da Venda | E3: Data Prevista Receb. | F3: Valor Bruto (R$) | G3: Taxa (%) | H3: Valor Líquido (R$) | I3: Status | J3: Data Recebimento | K3: Observações
A4: Visa/Master Credito | B4: Vendas cartao parceladas | C4: Cartao de Credito | D4: 10/01/2026 | E4: 10/02/2026 | F4: 1500 | G4: 0.0299 | H4: =IF(F4="","",F4*(1-G4)) -> 1455.15 | I4: =IF(E4="","",IF(J4<>"","Recebido",IF(E4<TODAY(),"Atrasado","Em Aberto"))) -> Em Aberto | K4: Repasse operadora D+30
H5: =IF(F5="","",F5*(1-G5)) | I5: =IF(E5="","",IF(J5<>"","Recebido",IF(E5<TODAY(),"Atrasado","Em Aberto")))
H6: =IF(F6="","",F6*(1-G6)) | I6: =IF(E6="","",IF(J6<>"","Recebido",IF(E6<TODAY(),"Atrasado","Em Aberto")))
H7: =IF(F7="","",F7*(1-G7)) | I7: =IF(E7="","",IF(J7<>"","Recebido",IF(E7<TODAY(),"Atrasado","Em Aberto")))
H8: =IF(F8="","",F8*(1-G8)) | I8: =IF(E8="","",IF(J8<>"","Recebido",IF(E8<TODAY(),"Atrasado","Em Aberto")))
H9: =IF(F9="","",F9*(1-G9)) | I9: =IF(E9="","",IF(J9<>"","Recebido",IF(E9<TODAY(),"Atrasado","Em Aberto")))
H10: =IF(F10="","",F10*(1-G10)) | I10: =IF(E10="","",IF(J10<>"","Recebido",IF(E10<TODAY(),"Atrasado","Em Aberto")))
H11: =IF(F11="","",F11*(1-G11)) | I11: =IF(E11="","",IF(J11<>"","Recebido",IF(E11<TODAY(),"Atrasado","Em Aberto")))
H12: =IF(F12="","",F12*(1-G12)) | I12: =IF(E12="","",IF(J12<>"","Recebido",IF(E12<TODAY(),"Atrasado","Em Aberto")))
H13: =IF(F13="","",F13*(1-G13)) | I13: =IF(E13="","",IF(J13<>"","Recebido",IF(E13<TODAY(),"Atrasado","Em Aberto")))
H14: =IF(F14="","",F14*(1-G14)) | I14: =IF(E14="","",IF(J14<>"","Recebido",IF(E14<TODAY(),"Atrasado","Em Aberto")))
H15: =IF(F15="","",F15*(1-G15)) | I15: =IF(E15="","",IF(J15<>"","Recebido",IF(E15<TODAY(),"Atrasado","Em Aberto")))
H16: =IF(F16="","",F16*(1-G16)) | I16: =IF(E16="","",IF(J16<>"","Recebido",IF(E16<TODAY(),"Atrasado","Em Aberto")))
... H83: =IF(F83="","",F83*(1-G83)) | I83: =IF(E83="","",IF(J83<>"","Recebido",IF(E83<TODAY(),"Atrasado","Em Aberto")))
A85: Total em Aberto | H85: =SUMIFS(H4:H83,I4:I83,"Em Aberto") -> 1455.15
A86: Total Atrasado | H86: =SUMIFS(H4:H83,I4:I83,"Atrasado") -> 0
A87: Total Recebido | H87: =SUMIFS(H4:H83,I4:I83,"Recebido") -> 0

Sheet Fluxo_Caixa_Projetado
A1: FLUXO DE CAIXA PROJETADO (12 MESES)
A3: Ano de Referência | B3: 2026
A4: Ref. início do mês (auxiliar - não editar) | B4: =DATE($B$3,1,1) -> 46023 | C4: =DATE($B$3,2,1) -> 46054 | D4: =DATE($B$3,3,1) -> 46082 | E4: =DATE($B$3,4,1) -> 46113 | F4: =DATE($B$3,5,1) -> 46143 | G4: =DATE($B$3,6,1) -> 46174 | H4: =DATE($B$3,7,1) -> 46204 | I4: =DATE($B$3,8,1) -> 46235 | J4: =DATE($B$3,9,1) -> 46266 | K4: =DATE($B$3,10,1) -> 46296 | L4: =DATE($B$3,11,1) -> 46327 | M4: =DATE($B$3,12,1) -> 46357
B5: =TEXT(B4,"mmm/aa") -> jan/26 | C5: =TEXT(C4,"mmm/aa") -> fev/26 | D5: =TEXT(D4,"mmm/aa") -> mar/26 | E5: =TEXT(E4,"mmm/aa") -> abr/26 | F5: =TEXT(F4,"mmm/aa") -> mai/26 | G5: =TEXT(G4,"mmm/aa") -> jun/26 | H5: =TEXT(H4,"mmm/aa") -> jul/26 | I5: =TEXT(I4,"mmm/aa") -> ago/26 | ... M5: =TEXT(M4,"mmm/aa") -> dez/26 | N5: Total Anual
A6: Saldo Inicial do Mês | B6: 0 | C6: =B16 -> 0 | D6: =C16 -> 0 | E6: =D16 -> 0 | F6: =E16 -> 0 | G6: =F16 -> 0 | H6: =G16 -> 0 | I6: =H16 -> 0 | J6: =I16 -> 0 | ... M6: =L16 -> 0 | N6: =B6 -> 0
A7: Entradas Previstas
A8: Vendas à Vista (Dinheiro/PIX/Débito) | B8: 0 | C8: 0 | D8: 0 | E8: 0 | F8: 0 | G8: 0 | H8: 0 | I8: 0 | J8: 0 | K8: 0 | L8: 0 | M8: 0 | N8: =SUM(B8:M8) -> 0
A9: Recebimentos Cartão Crédito/Convênio | B9: =SUMIFS(Contas_a_Receber!$H$4:$H$83,Contas_a_Receber!$E$4:$E$83,">="&B4,Contas_a_Receber!$E$4:$E$83,"<"&EDATE(B4,1)) -> 0 | C9: =SUMIFS(Contas_a_Receber!$H$4:$H$83,Contas_a_Receber!$E$4:$E$83,">="&C4,Contas_a_Receber!$E$4:$E$83,"<"&EDATE(C4,1)) -> 0 | D9: =SUMIFS(Contas_a_Receber!$H$4:$H$83,Contas_a_Receber!$E$4:$E$83,">="&D4,Contas_a_Receber!$E$4:$E$83,"<"&EDATE(D4,1)) -> 0 | E9: =SUMIFS(Contas_a_Receber!$H$4:$H$83,Contas_a_Receber!$E$4:$E$83,">="&E4,Contas_a_Receber!$E$4:$E$83,"<"&EDATE(E4,1)) -> 0 | F9: =SUMIFS(Contas_a_Receber!$H$4:$H$83,Contas_a_Receber!$E$4:$E$83,">="&F4,Contas_a_Receber!$E$4:$E$83,"<"&EDATE(F4,1)) -> 0 | G9: =SUMIFS(Contas_a_Receber!$H$4:$H$83,Contas_a_Receber!$E$4:$E$83,">="&G4,Contas_a_Receber!$E$4:$E$83,"<"&EDATE(G4,1)) -> 0 | H9: =SUMIFS(Contas_a_Receber!$H$4:$H$83,Contas_a_Receber!$E$4:$E$83,">="&H4,Contas_a_Receber!$E$4:$E$83,"<"&EDATE(H4,1)) -> 0 | I9: =SUMIFS(Contas_a_Receber!$H$4:$H$83,Contas_a_Receber!$E$4:$E$83,">="&I4,Contas_a_Receber!$E$4:$E$83,"<"&EDATE(I4,1)) -> 0 | ... M9: =SUMIFS(Contas_a_Receber!$H$4:$H$83,Contas_a_Receber!$E$4:$E$83,">="&M4,Contas_a_Receber!$E$4:$E$83,"<"&EDATE(M4,1)) -> 0 | N9: =SUM(B9:M9) -> 0
A10: Outras Entradas | B10: 0 | C10: 0 | D10: 0 | E10: 0 | F10: 0 | G10: 0 | H10: 0 | I10: 0 | J10: 0 | K10: 0 | L10: 0 | M10: 0 | N10: =SUM(B10:M10) -> 0
A11: Total de Entradas | B11: =SUM(B8:B10) -> 0 | C11: =SUM(C8:C10) -> 0 | D11: =SUM(D8:D10) -> 0 | E11: =SUM(E8:E10) -> 0 | F11: =SUM(F8:F10) -> 0 | G11: =SUM(G8:G10) -> 0 | H11: =SUM(H8:H10) -> 0 | I11: =SUM(I8:I10) -> 0 | ... M11: =SUM(M8:M10) -> 0 | N11: =SUM(B11:M11) -> 0
A12: Saídas Previstas
A13: Pagamentos Previstos (Contas a Pagar) | B13: =SUMIFS(Contas_a_Pagar!$F$4:$F$83,Contas_a_Pagar!$E$4:$E$83,">="&B4,Contas_a_Pagar!$E$4:$E$83,"<"&EDATE(B4,1)) -> 0 | C13: =SUMIFS(Contas_a_Pagar!$F$4:$F$83,Contas_a_Pagar!$E$4:$E$83,">="&C4,Contas_a_Pagar!$E$4:$E$83,"<"&EDATE(C4,1)) -> 0 | D13: =SUMIFS(Contas_a_Pagar!$F$4:$F$83,Contas_a_Pagar!$E$4:$E$83,">="&D4,Contas_a_Pagar!$E$4:$E$83,"<"&EDATE(D4,1)) -> 0 | E13: =SUMIFS(Contas_a_Pagar!$F$4:$F$83,Contas_a_Pagar!$E$4:$E$83,">="&E4,Contas_a_Pagar!$E$4:$E$83,"<"&EDATE(E4,1)) -> 0 | F13: =SUMIFS(Contas_a_Pagar!$F$4:$F$83,Contas_a_Pagar!$E$4:$E$83,">="&F4,Contas_a_Pagar!$E$4:$E$83,"<"&EDATE(F4,1)) -> 0 | G13: =SUMIFS(Contas_a_Pagar!$F$4:$F$83,Contas_a_Pagar!$E$4:$E$83,">="&G4,Contas_a_Pagar!$E$4:$E$83,"<"&EDATE(G4,1)) -> 0 | H13: =SUMIFS(Contas_a_Pagar!$F$4:$F$83,Contas_a_Pagar!$E$4:$E$83,">="&H4,Contas_a_Pagar!$E$4:$E$83,"<"&EDATE(H4,1)) -> 0 | I13: =SUMIFS(Contas_a_Pagar!$F$4:$F$83,Contas_a_Pagar!$E$4:$E$83,">="&I4,Contas_a_Pagar!$E$4:$E$83,"<"&EDATE(I4,1)) -> 0 | ... M13: =SUMIFS(Contas_a_Pagar!$F$4:$F$83,Contas_a_Pagar!$E$4:$E$83,">="&M4,Contas_a_Pagar!$E$4:$E$83,"<"&EDATE(M4,1)) -> 0 | N13: =SUM(B13:M13) -> 0
A14: Outras Saídas (não cadastradas em Contas a Pagar) | B14: 0 | C14: 0 | D14: 0 | E14: 0 | F14: 0 | G14: 0 | H14: 0 | I14: 0 | J14: 0 | K14: 0 | L14: 0 | M14: 0 | N14: =SUM(B14:M14) -> 0
A15: Total de Saídas | B15: =SUM(B13:B14) -> 0 | C15: =SUM(C13:C14) -> 0 | D15: =SUM(D13:D14) -> 0 | E15: =SUM(E13:E14) -> 0 | F15: =SUM(F13:F14) -> 0 | G15: =SUM(G13:G14) -> 0 | H15: =SUM(H13:H14) -> 0 | I15: =SUM(I13:I14) -> 0 | ... M15: =SUM(M13:M14) -> 0 | N15: =SUM(B15:M15) -> 0
A16: Saldo Final do Mês | B16: =B6+B11-B15 -> 0 | C16: =C6+C11-C15 -> 0 | D16: =D6+D11-D15 -> 0 | E16: =E6+E11-E15 -> 0 | F16: =F6+F11-F15 -> 0 | G16: =G6+G11-G15 -> 0 | H16: =H6+H11-H15 -> 0 | I16: =I6+I11-I15 -> 0 | ... M16: =M6+M11-M15 -> 0 | N16: =M16 -> 0
A18: Análise de Cenários (sensibilidade sobre o Total de Entradas)
A19: Variação Otimista (%) | B19: 0.1
A20: Variação Pessimista (%) | B20: -0.1
A21: Saldo Final Otimista | B21: =B16+B11*$B$19 -> 0 | C21: =C16+C11*$B$19 -> 0 | D21: =D16+D11*$B$19 -> 0 | E21: =E16+E11*$B$19 -> 0 | F21: =F16+F11*$B$19 -> 0 | G21: =G16+G11*$B$19 -> 0 | H21: =H16+H11*$B$19 -> 0 | I21: =I16+I11*$B$19 -> 0 | ... M21: =M16+M11*$B$19 -> 0 | N21: =M21 -> 0
A22: Saldo Final Pessimista | B22: =B16+B11*$B$20 -> 0 | C22: =C16+C11*$B$20 -> 0 | D22: =D16+D11*$B$20 -> 0 | E22: =E16+E11*$B$20 -> 0 | F22: =F16+F11*$B$20 -> 0 | G22: =G16+G11*$B$20 -> 0 | H22: =H16+H11*$B$20 -> 0 | I22: =I16+I11*$B$20 -> 0 | ... M22: =M16+M11*$B$20 -> 0 | N22: =M22 -> 0

Sheet DRE_Gerencial
A1: DRE GERENCIAL E INDICADORES (12 MESES)
A3: Ano de Referência | B3: 2026
A4: Alíquota de Impostos sobre Vendas (Simples Nacional) (%) | B4: 0.04
A6: Ref. início do mês (auxiliar - não editar) | B6: =DATE($B$3,1,1) -> 46023 | C6: =DATE($B$3,2,1) -> 46054 | D6: =DATE($B$3,3,1) -> 46082 | E6: =DATE($B$3,4,1) -> 46113 | F6: =DATE($B$3,5,1) -> 46143 | G6: =DATE($B$3,6,1) -> 46174 | H6: =DATE($B$3,7,1) -> 46204 | I6: =DATE($B$3,8,1) -> 46235 | J6: =DATE($B$3,9,1) -> 46266 | K6: =DATE($B$3,10,1) -> 46296 | L6: =DATE($B$3,11,1) -> 46327 | M6: =DATE($B$3,12,1) -> 46357
B7: =TEXT(B6,"mmm/aa") -> jan/26 | C7: =TEXT(C6,"mmm/aa") -> fev/26 | D7: =TEXT(D6,"mmm/aa") -> mar/26 | E7: =TEXT(E6,"mmm/aa") -> abr/26 | F7: =TEXT(F6,"mmm/aa") -> mai/26 | G7: =TEXT(G6,"mmm/aa") -> jun/26 | H7: =TEXT(H6,"mmm/aa") -> jul/26 | I7: =TEXT(I6,"mmm/aa") -> ago/26 | ... M7: =TEXT(M6,"mmm/aa") -> dez/26 | N7: Total Anual
A8: Receita Bruta de Vendas | B8: 0 | C8: 0 | D8: 0 | E8: 0 | F8: 0 | G8: 0 | H8: 0 | I8: 0 | J8: 0 | K8: 0 | L8: 0 | M8: 0 | N8: =SUM(B8:M8) -> 0
A9: (-) Devoluções e Cancelamentos | B9: 0 | C9: 0 | D9: 0 | E9: 0 | F9: 0 | G9: 0 | H9: 0 | I9: 0 | J9: 0 | K9: 0 | L9: 0 | M9: 0 | N9: =SUM(B9:M9) -> 0
A10: (-) Impostos sobre Vendas | B10: =B8*$B$4 -> 0 | C10: =C8*$B$4 -> 0 | D10: =D8*$B$4 -> 0 | E10: =E8*$B$4 -> 0 | F10: =F8*$B$4 -> 0 | G10: =G8*$B$4 -> 0 | H10: =H8*$B$4 -> 0 | I10: =I8*$B$4 -> 0 | ... M10: =M8*$B$4 -> 0 | N10: =SUM(B10:M10) -> 0
A11: =Receita Líquida -> #NAME? | B11: =B8-B9-B10 -> 0 | C11: =C8-C9-C10 -> 0 | D11: =D8-D9-D10 -> 0 | E11: =E8-E9-E10 -> 0 | F11: =F8-F9-F10 -> 0 | G11: =G8-G9-G10 -> 0 | H11: =H8-H9-H10 -> 0 | I11: =I8-I9-I10 -> 0 | ... M11: =M8-M9-M10 -> 0 | N11: =SUM(B11:M11) -> 0
A12: (-) CMV (Custo da Mercadoria Vendida) | B12: 0 | C12: 0 | D12: 0 | E12: 0 | F12: 0 | G12: 0 | H12: 0 | I12: 0 | J12: 0 | K12: 0 | L12: 0 | M12: 0 | N12: =SUM(B12:M12) -> 0
A13: =Lucro Bruto -> #NAME? | B13: =B11-B12 -> 0 | C13: =C11-C12 -> 0 | D13: =D11-D12 -> 0 | E13: =E11-E12 -> 0 | F13: =F11-F12 -> 0 | G13: =G11-G12 -> 0 | H13: =H11-H12 -> 0 | I13: =I11-I12 -> 0 | ... M13: =M11-M12 -> 0 | N13: =SUM(B13:M13) -> 0
A14: Margem Bruta (%) | B14: =IFERROR(B13/B11,0) -> 0 | C14: =IFERROR(C13/C11,0) -> 0 | D14: =IFERROR(D13/D11,0) -> 0 | E14: =IFERROR(E13/E11,0) -> 0 | F14: =IFERROR(F13/F11,0) -> 0 | G14: =IFERROR(G13/G11,0) -> 0 | H14: =IFERROR(H13/H11,0) -> 0 | I14: =IFERROR(I13/I11,0) -> 0 | ... N14: =IFERROR(N13/N11,0) -> 0
A16: Despesas Operacionais
A17: Salários e Encargos | B17: 0 | C17: 0 | D17: 0 | E17: 0 | F17: 0 | G17: 0 | H17: 0 | I17: 0 | J17: 0 | K17: 0 | L17: 0 | M17: 0 | N17: =SUM(B17:M17) -> 0
A18: Aluguel | B18: 0 | C18: 0 | D18: 0 | E18: 0 | F18: 0 | G18: 0 | H18: 0 | I18: 0 | J18: 0 | K18: 0 | L18: 0 | M18: 0 | N18: =SUM(B18:M18) -> 0
A19: Energia e Água | B19: 0 | C19: 0 | D19: 0 | E19: 0 | F19: 0 | G19: 0 | H19: 0 | I19: 0 | J19: 0 | K19: 0 | L19: 0 | M19: 0 | N19: =SUM(B19:M19) -> 0
A20: Materiais e Embalagens | B20: 0 | C20: 0 | D20: 0 | E20: 0 | F20: 0 | G20: 0 | H20: 0 | I20: 0 | J20: 0 | K20: 0 | L20: 0 | M20: 0 | N20: =SUM(B20:M20) -> 0
A21: Marketing | B21: 0 | C21: 0 | D21: 0 | E21: 0 | F21: 0 | G21: 0 | H21: 0 | I21: 0 | J21: 0 | K21: 0 | L21: 0 | M21: 0 | N21: =SUM(B21:M21) -> 0
A22: Outras Despesas Operacionais | B22: 0 | C22: 0 | D22: 0 | E22: 0 | F22: 0 | G22: 0 | H22: 0 | I22: 0 | J22: 0 | K22: 0 | L22: 0 | M22: 0 | N22: =SUM(B22:M22) -> 0
A23: Total de Despesas Operacionais | B23: =SUM(B17:B22) -> 0 | C23: =SUM(C17:C22) -> 0 | D23: =SUM(D17:D22) -> 0 | E23: =SUM(E17:E22) -> 0 | F23: =SUM(F17:F22) -> 0 | G23: =SUM(G17:G22) -> 0 | H23: =SUM(H17:H22) -> 0 | I23: =SUM(I17:I22) -> 0 | ... M23: =SUM(M17:M22) -> 0 | N23: =SUM(B23:M23) -> 0
A24: =Resultado Operacional (EBITDA) -> #NAME? | B24: =B13-B23 -> 0 | C24: =C13-C23 -> 0 | D24: =D13-D23 -> 0 | E24: =E13-E23 -> 0 | F24: =F13-F23 -> 0 | G24: =G13-G23 -> 0 | H24: =H13-H23 -> 0 | I24: =I13-I23 -> 0 | ... M24: =M13-M23 -> 0 | N24: =SUM(B24:M24) -> 0
A25: Margem Operacional (%) | B25: =IFERROR(B24/B11,0) -> 0 | C25: =IFERROR(C24/C11,0) -> 0 | D25: =IFERROR(D24/D11,0) -> 0 | E25: =IFERROR(E24/E11,0) -> 0 | F25: =IFERROR(F24/F11,0) -> 0 | G25: =IFERROR(G24/G11,0) -> 0 | H25: =IFERROR(H24/H11,0) -> 0 | I25: =IFERROR(I24/I11,0) -> 0 | ... N25: =IFERROR(N24/N11,0) -> 0
A27: (-) Despesas Financeiras | B27: 0 | C27: 0 | D27: 0 | E27: 0 | F27: 0 | G27: 0 | H27: 0 | I27: 0 | J27: 0 | K27: 0 | L27: 0 | M27: 0 | N27: =SUM(B27:M27) -> 0
A28: (+) Receitas Financeiras | B28: 0 | C28: 0 | D28: 0 | E28: 0 | F28: 0 | G28: 0 | H28: 0 | I28: 0 | J28: 0 | K28: 0 | L28: 0 | M28: 0 | N28: =SUM(B28:M28) -> 0
A29: =Resultado Líquido do Período -> #NAME? | B29: =B24-B27+B28 -> 0 | C29: =C24-C27+C28 -> 0 | D29: =D24-D27+D28 -> 0 | E29: =E24-E27+E28 -> 0 | F29: =F24-F27+F28 -> 0 | G29: =G24-G27+G28 -> 0 | H29: =H24-H27+H28 -> 0 | I29: =I24-I27+I28 -> 0 | ... M29: =M24-M27+M28 -> 0 | N29: =SUM(B29:M29) -> 0
A30: Margem Líquida (%) | B30: =IFERROR(B29/B11,0) -> 0 | C30: =IFERROR(C29/C11,0) -> 0 | D30: =IFERROR(D29/D11,0) -> 0 | E30: =IFERROR(E29/E11,0) -> 0 | F30: =IFERROR(F29/F11,0) -> 0 | G30: =IFERROR(G29/G11,0) -> 0 | H30: =IFERROR(H29/H11,0) -> 0 | I30: =IFERROR(I29/I11,0) -> 0 | ... N30: =IFERROR(N29/N11,0) -> 0
A32: Indicadores Gerenciais
A33: Ponto de Equilíbrio Mensal (R$) | B33: =IFERROR(B23/B14,0) -> 0 | C33: =IFERROR(C23/C14,0) -> 0 | D33: =IFERROR(D23/D14,0) -> 0 | E33: =IFERROR(E23/E14,0) -> 0 | F33: =IFERROR(F23/F14,0) -> 0 | G33: =IFERROR(G23/G14,0) -> 0 | H33: =IFERROR(H23/H14,0) -> 0 | I33: =IFERROR(I23/I14,0) -> 0 | ... N33: =IFERROR(N23/N14,0) -> 0
A34: Número de Vendas no Mês (Cupons) | B34: 0 | C34: 0 | D34: 0 | E34: 0 | F34: 0 | G34: 0 | H34: 0 | I34: 0 | J34: 0 | K34: 0 | L34: 0 | M34: 0 | N34: =SUM(B34:M34) -> 0
A35: Ticket Médio (R$) | B35: =IFERROR(B8/B34,0) -> 0 | C35: =IFERROR(C8/C34,0) -> 0 | D35: =IFERROR(D8/D34,0) -> 0 | E35: =IFERROR(E8/E34,0) -> 0 | F35: =IFERROR(F8/F34,0) -> 0 | G35: =IFERROR(G8/G34,0) -> 0 | H35: =IFERROR(H8/H34,0) -> 0 | I35: =IFERROR(I8/I34,0) -> 0 | ... N35: =IFERROR(N8/N34,0) -> 0
